specsync/__init__.py
specsync/__main__.py
specsync/cli.py
specsync/config.py
specsync/exceptions.py
specsync/frontmatter.py
specsync/fs.py
specsync/logging.py
specsync/models.py
specsync/prompt.py
specsync/selector.py
specsync/sync.py
specsync-0.1.0.dist-info/WHEEL
specsync-0.1.0.dist-info/entry_points.txt
specsync-0.1.0.dist-info/METADATA
specsync-0.1.0.dist-info/RECORD
