Metadata-Version: 2.3
Name: specsync
Version: 0.1.0
Summary: Synchronize markdown specifications between a git repo and external workspace.
Author: Specsync Team
Requires-Dist: pyyaml>=6.0
Requires-Python: >=3.11
